matrixscore/__init__.py
matrixscore/matrixscore_cli.py
matrixscore/core/__init__.py
matrixscore/core/api.py
matrixscore/core/cache.py
matrixscore/core/constants.py
matrixscore/core/schema.py
matrixscore/core/scoring.py
matrixscore-0.1.0.dist-info/licenses/LICENSE
matrixscore-0.1.0.dist-info/METADATA
matrixscore-0.1.0.dist-info/WHEEL
matrixscore-0.1.0.dist-info/entry_points.txt
matrixscore-0.1.0.dist-info/top_level.txt
matrixscore-0.1.0.dist-info/RECORD
