Metadata-Version: 2.4
Name: matrixscore
Version: 0.1.0
Summary: A domain-agnostic scoring engine for issue/capability coverage
Author: Eric Gilligan
License: MIT
Keywords: scoring,risk,portfolio,coverage,capability
Classifier: Programming Language :: Python :: 3
Classifier: License :: OSI Approved :: MIT License
Classifier: Operating System :: OS Independent
Requires-Python: >=3.9
License-File: LICENSE
Dynamic: license-file
